zsh_startify/__init__.py
zsh_startify/__main__.py
zsh_startify-0.3.0.dist-info/LICENSE
zsh_startify-0.3.0.dist-info/METADATA
zsh_startify-0.3.0.dist-info/WHEEL
zsh_startify-0.3.0.dist-info/entry_points.txt
zsh_startify-0.3.0.dist-info/top_level.txt
zsh_startify-0.3.0.dist-info/RECORD
