Metadata-Version: 2.1
Name: zsh-startify
Version: 0.3.0
Summary: Fancy start screen for zsh w/ tmux integration and more!
Home-page: https://github.com/alichtman/zsh-startify
Author: Aaron Lichtman
Author-email: aaronlichtman@gmail.com
License: MIT
Platform: UNKNOWN
Classifier: License :: OSI Approved :: MIT License
Classifier: Programming Language :: Python
Classifier: Programming Language :: Python :: 3
Classifier: Programming Language :: Python :: 3.6
Classifier: Programming Language :: Python :: Implementation :: CPython
Classifier: Programming Language :: Python :: Implementation :: PyPy
Requires-Python: >=3.6.0
Requires-Dist: libtmux
Requires-Dist: halo
Requires-Dist: pyfiglet
Requires-Dist: colorama
Requires-Dist: PyInquirer
